setup.cfg
setup.py
py509/__init__.py
py509/client.py
py509/extensions.py
py509/utils.py
py509/x509.py
py509.egg-info/PKG-INFO
py509.egg-info/SOURCES.txt
py509.egg-info/dependency_links.txt
py509.egg-info/entry_points.txt
py509.egg-info/requires.txt
py509.egg-info/top_level.txt
py509/bin/__init__.py
py509/bin/diff.py
py509/bin/get.py
py509/bin/ls.py
py509/bin/verify.py
test/test_extensions.py
test/test_x509.py